entropy_classifier/__init__.py
entropy_classifier/entropy_calculate.py
entropy_classifier/file_import.py
entropy_classifier/uncertainty_classification.py
entropy_classifier-1.1.0.dist-info/METADATA
entropy_classifier-1.1.0.dist-info/WHEEL
entropy_classifier-1.1.0.dist-info/top_level.txt
entropy_classifier-1.1.0.dist-info/RECORD
