Metadata-Version: 2.1
Name: entropy-classifier
Version: 1.1.0
Summary: A library to calculate entropy and classify data based on uncertainty.
Home-page: https://github.com/moudgalya1223/LLM_business
Author: moudgalya
Author-email: dattu99rockstar@gmail.com
Classifier: Programming Language :: Python :: 3
Classifier: License :: OSI Approved :: MIT License
Classifier: Operating System :: OS Independent
Requires-Python: >=3.6
Requires-Dist: pandas >=1.3.0
Requires-Dist: numpy >=1.21.0
